LICENSE
MANIFEST.in
README.md
pyproject.toml
setup.py
./LICENSE
./README.md
quickpub/__init__.py
quickpub/__main__.py
quickpub/classifiers.py
quickpub/enforcers.py
quickpub/files.py
quickpub/logging_.py
quickpub/proxy.py
quickpub/py.typed
quickpub/qa.py
quickpub/validators.py
quickpub/worker_pool.py
quickpub.egg-info/PKG-INFO
quickpub.egg-info/SOURCES.txt
quickpub.egg-info/dependency_links.txt
quickpub.egg-info/entry_points.txt
quickpub.egg-info/requires.txt
quickpub.egg-info/top_level.txt
quickpub/strategies/__init__.py
quickpub/strategies/build_schema.py
quickpub/strategies/constraint_enforcer.py
quickpub/strategies/python_provider.py
quickpub/strategies/quality_assurance_runner.py
quickpub/strategies/quickpub_strategy.py
quickpub/strategies/upload_target.py
quickpub/strategies/implementations/__init__.py
quickpub/strategies/implementations/build_schemas/__init__.py
quickpub/strategies/implementations/build_schemas/setuptools_build_schema.py
quickpub/strategies/implementations/constraint_enforcers/__init__.py
quickpub/strategies/implementations/constraint_enforcers/license_enforcer.py
quickpub/strategies/implementations/constraint_enforcers/local_version_enforcer.py
quickpub/strategies/implementations/constraint_enforcers/pypi_remote_version_enforcer.py
quickpub/strategies/implementations/constraint_enforcers/pypirc_enforcer.py
quickpub/strategies/implementations/constraint_enforcers/readme_enforcer.py
quickpub/strategies/implementations/python_providers/__init__.py
quickpub/strategies/implementations/python_providers/conda_python_provider.py
quickpub/strategies/implementations/python_providers/default_python_provider.py
quickpub/strategies/implementations/quality_assurance_runners/__init__.py
quickpub/strategies/implementations/quality_assurance_runners/mypy_qa_runner.py
quickpub/strategies/implementations/quality_assurance_runners/pylint_qa_runner.py
quickpub/strategies/implementations/quality_assurance_runners/pytest_qa_runner.py
quickpub/strategies/implementations/quality_assurance_runners/unittest_qa_runner.py
quickpub/strategies/implementations/upload_targets/__init__.py
quickpub/strategies/implementations/upload_targets/github_upload_target.py
