Metadata-Version: 2.4
Name: quickpub
Version: 4.0.0
Summary: A local CI/CD simulation tool that runs quality checks, tests, and validations locally before publishing Python packages, ensuring higher build pass rates and faster feedback loops
Author-email: danielnachumdev <danielnachumdev@gmail.com>
License: MIT License
Project-URL: Homepage, https://github.com/danielnachumdev/quickpub
Project-URL: Bug Tracker, https://github.com/danielnachumdev/quickpub/issues
Classifier: Development Status :: 3 - Alpha
Classifier: Intended Audience :: Developers
Classifier: Programming Language :: Python :: 3
Classifier: Operating System :: Microsoft :: Windows
Requires-Python: >=3.8.0
License-File: LICENSE
Requires-Dist: danielutils>=1.0.0
Requires-Dist: requests
Requires-Dist: fire
Dynamic: license-file
